hanzo_tools/__init__.py
hanzo_tools/jupyter/__init__.py
hanzo_tools/jupyter/base.py
hanzo_tools/jupyter/jupyter.py
hanzo_tools/jupyter/notebook_edit.py
hanzo_tools/jupyter/notebook_read.py
hanzo_tools_jupyter-0.2.0.dist-info/METADATA
hanzo_tools_jupyter-0.2.0.dist-info/WHEEL
hanzo_tools_jupyter-0.2.0.dist-info/entry_points.txt
hanzo_tools_jupyter-0.2.0.dist-info/top_level.txt
hanzo_tools_jupyter-0.2.0.dist-info/RECORD
